deepobfuscode/__init__.py
deepobfuscode/encryption.py
deepobfuscode/execution.py
deepobfuscode/util.py
deepobfuscode-1.0.0.dist-info/METADATA
deepobfuscode-1.0.0.dist-info/WHEEL
deepobfuscode-1.0.0.dist-info/top_level.txt
deepobfuscode-1.0.0.dist-info/RECORD
